odoo/addons/pms_partner_second_lastname/README.rst
odoo/addons/pms_partner_second_lastname/__init__.py
odoo/addons/pms_partner_second_lastname/__manifest__.py
odoo/addons/pms_partner_second_lastname/i18n/es.po
odoo/addons/pms_partner_second_lastname/i18n/it.po
odoo/addons/pms_partner_second_lastname/i18n/pms_partner_second_lastname.pot
odoo/addons/pms_partner_second_lastname/models/__init__.py
odoo/addons/pms_partner_second_lastname/models/pms_checkin_partner.py
odoo/addons/pms_partner_second_lastname/readme/CONTEXT.rst
odoo/addons/pms_partner_second_lastname/readme/CONTRIBUTORS.rst
odoo/addons/pms_partner_second_lastname/readme/DESCRIPTION.rst
odoo/addons/pms_partner_second_lastname/static/description/icon.png
odoo/addons/pms_partner_second_lastname/static/description/index.html
odoo/addons/pms_partner_second_lastname/views/pms_checkin_partner.xml
odoo/addons/pms_partner_second_lastname/views/res_partner.xml
odoo/addons/pms_partner_second_lastname/views/traveller_report_template.xml
odoo_addon_pms_partner_second_lastname-16.0.2.1.0.4.dist-info/METADATA
odoo_addon_pms_partner_second_lastname-16.0.2.1.0.4.dist-info/WHEEL
odoo_addon_pms_partner_second_lastname-16.0.2.1.0.4.dist-info/top_level.txt
odoo_addon_pms_partner_second_lastname-16.0.2.1.0.4.dist-info/RECORD
